adbpg_mcp_server/__init__.py
adbpg_mcp_server/__main__.py
adbpg_mcp_server/adbpg.py
adbpg_mcp_server/adbpg_basic_operation.py
adbpg_mcp_server/adbpg_config.py
adbpg_mcp_server/adbpg_graphrag.py
adbpg_mcp_server/adbpg_memory.py
adbpg_mcp_server/server_http.py
adbpg_mcp_server/server_stdio.py
iflow_mcp_aliyun_adbpg_mcp_server-2.0.0.dist-info/licenses/LICENSE
iflow_mcp_aliyun_adbpg_mcp_server-2.0.0.dist-info/METADATA
iflow_mcp_aliyun_adbpg_mcp_server-2.0.0.dist-info/WHEEL
iflow_mcp_aliyun_adbpg_mcp_server-2.0.0.dist-info/entry_points.txt
iflow_mcp_aliyun_adbpg_mcp_server-2.0.0.dist-info/top_level.txt
iflow_mcp_aliyun_adbpg_mcp_server-2.0.0.dist-info/RECORD
