Metadata-Version: 2.4
Name: iflow-mcp_aliyun_adbpg-mcp-server
Version: 2.0.0
Summary: AnalyticDB PostgreSQL MCP Server serves as a universal interface between AI Agents and AnalyticDB PostgreSQL databases. It enables seamless communication between AI Agents and AnalyticDB PostgreSQL, helping AI Agents retrieve database metadata and execute SQL operations.
Requires-Python: >=3.11
License-File: LICENSE
Requires-Dist: mcp>=1.13.1
Requires-Dist: psycopg>=3.2.10
Requires-Dist: requests>=2.32.5
Dynamic: license-file
